{
    "objects": [
        {
            "object_ID": 1,
            "length": 78914
        },
        {
            "object_ID": 4,
            "length": 49930
        },
        {
            "object_ID": 2,
            "length": 7321
        },
        {
            "object_ID": 12,
            "length": 35967
        },
        {
            "object_ID": 108,
            "length": 663
        },
        {
            "object_ID": 43,
            "length": 617
        },
        {
            "object_ID": 20,
            "length": 5641
        },
        {
            "object_ID": 6,
            "length": 40402
        },
        {
            "object_ID": 127,
            "length": 5311
        },
        {
            "object_ID": 11,
            "length": 4861
        },
        {
            "object_ID": 115,
            "length": 773
        }
    ]
}