{
    "objects": [
        {
            "object_ID": 0,
            "length": 67247
        },
        {
            "object_ID": 2,
            "length": 30365
        },
        {
            "object_ID": 17,
            "length": 24736
        },
        {
            "object_ID": 22,
            "length": 3298
        },
        {
            "object_ID": 12,
            "length": 4681
        },
        {
            "object_ID": 51,
            "length": 1822
        },
        {
            "object_ID": 15,
            "length": 3354
        },
        {
            "object_ID": 3,
            "length": 94896
        },
        {
            "object_ID": 125,
            "length": 1
        }
    ]
}