{
    "objects": [
        {
            "object_ID": 1,
            "length": 109540
        },
        {
            "object_ID": 123,
            "length": 1106
        },
        {
            "object_ID": 43,
            "length": 2479
        },
        {
            "object_ID": 86,
            "length": 214
        },
        {
            "object_ID": 12,
            "length": 54418
        },
        {
            "object_ID": 116,
            "length": 50198
        },
        {
            "object_ID": 115,
            "length": 3498
        },
        {
            "object_ID": 6,
            "length": 8947
        }
    ]
}