{
    "objects": [
        {
            "object_ID": 1,
            "length": 134314
        },
        {
            "object_ID": 2,
            "length": 28616
        },
        {
            "object_ID": 93,
            "length": 420
        },
        {
            "object_ID": 119,
            "length": 723
        },
        {
            "object_ID": 12,
            "length": 14594
        },
        {
            "object_ID": 43,
            "length": 485
        },
        {
            "object_ID": 4,
            "length": 1921
        },
        {
            "object_ID": 20,
            "length": 546
        },
        {
            "object_ID": 6,
            "length": 37054
        },
        {
            "object_ID": 17,
            "length": 35
        },
        {
            "object_ID": 0,
            "length": 11692
        }
    ]
}