{
    "objects": [
        {
            "object_ID": 4,
            "length": 37172
        },
        {
            "object_ID": 2,
            "length": 37328
        },
        {
            "object_ID": 93,
            "length": 4083
        },
        {
            "object_ID": 80,
            "length": 69642
        },
        {
            "object_ID": 72,
            "length": 241
        },
        {
            "object_ID": 12,
            "length": 17856
        },
        {
            "object_ID": 20,
            "length": 1023
        },
        {
            "object_ID": 9,
            "length": 1747
        },
        {
            "object_ID": 6,
            "length": 60996
        },
        {
            "object_ID": 102,
            "length": 312
        }
    ]
}